1. run
#+BEGIN_SRC shell
python test.py
#+END_SRC
2. output
#+BEGIN_SRC text
 33           0 LOAD_CONST               1 (3)
              2 STORE_GLOBAL             0 (a)

 34           4 LOAD_GLOBAL              0 (a)
              6 LOAD_CONST               2 (1)
              8 BINARY_ADD
             10 STORE_FAST               1 (b)

 35          12 LOAD_FAST                1 (b)
             14 LOAD_CONST               2 (1)
             16 BINARY_ADD
             18 STORE_FAST               2 (c)

 36          20 LOAD_FAST                2 (c)
             22 LOAD_CONST               2 (1)
             24 BINARY_ADD
             26 STORE_FAST               3 (d)

 37          28 LOAD_GLOBAL              0 (a)
             30 LOAD_FAST                1 (b)
             32 BINARY_MULTIPLY
             34 LOAD_FAST                2 (c)
             36 BINARY_MULTIPLY
             38 LOAD_FAST                3 (d)
             40 BINARY_TRUE_DIVIDE
             42 STORE_FAST               4 (e)

 38          44 LOAD_FAST                4 (e)
             46 LOAD_FAST                4 (e)
             48 LOAD_FAST                4 (e)
             50 BUILD_TUPLE              3
             52 STORE_FAST               5 (f)

 39          54 LOAD_FAST                5 (f)
             56 LOAD_CONST               3 (2)
             58 BINARY_SUBSCR
             60 LOAD_FAST                0 (g)
             62 BUILD_TUPLE              2
             64 RETURN_VALUE
----------------------------------------------------------------------------------------------------
 33           0 LOAD_CONST               9 (10.0)
              2 LOAD_CONST               9 (10.0)

 34           4 LOAD_CONST               9 (10.0)
              6 BUILD_TUPLE              3
              8 STORE_FAST               5 (f)
             10 LOAD_FAST                5 (f)

 35          12 LOAD_CONST               3 (2)
             14 BINARY_SUBSCR
             16 LOAD_FAST                0 (g)
             18 BUILD_TUPLE              2

 36          20 RETURN_VALUE
----------------------------------------------------------------------------------------------------
before             0.6187772
after              0.2790337
after < before     True
before / after     2.2175715693122373
test()             (10.0, 0)
example()          (10.0, 0)
#+END_SRC